{
  "meta": {
    "source_pdf": "Biblia-in-limba-romana-Dumitru Cornilescu-page 5.pdf",
    "generated_at_epoch": 1771862787
  },
  "book": "Geneza",
  "chapter": {
    "number": 1,
    "subtitle": "Vremurile străvechi de la facerea lumii până la Avraam*",
    "title": "Facerea lumii",
    "verses": [
      {
        "n": 1,
        "text": "La început, Dumnezeu a făcut cerurile şi pământul."
      },
      {
        "n": 2,
        "text": "Pământul era pustiu şi gol; peste faţa adâncului de ape era întuneric, şi Duhul lui Dumnezeu Se mişca pe deasupra apelor."
      },
      {
        "n": 3,
        "text": "Dumnezeu a zis: „Să fie lumină!” Şi a fost lumină."
      },
      {
        "n": 4,
        "text": "Dumnezeu a văzut că lumina era bună; şi Dumnezeu a despărţit lumina de întuneric."
      },
      {
        "n": 5,
        "text": "Dumnezeu a numit lumina zi, iar întunericul l-a numit noapte. Astfel, a fost o seară, şi apoi a fost o dimineaţă: aceasta a fost ziua întâi."
      },
      {
        "n": 6,
        "text": "Dumnezeu a zis: „Să fie o întindere între ape, şi ea să despartă apele de ape.”"
      },
      {
        "n": 7,
        "text": "Şi Dumnezeu a făcut întinderea, şi ea a despărţit apele care sunt dedesubtul întinderii de apele care sunt deasupra întinderii. Şi aşa a fost."
      },
      {
        "n": 8,
        "text": "Dumnezeu a numit întinderea cer. Astfel, a fost o seară, şi apoi a fost o dimineaţă: aceasta a fost ziua a doua."
      },
      {
        "n": 9,
        "text": "Dumnezeu a zis: „Să se strângă la un loc apele care sunt dedesubtul cerului şi să se arate uscatul!” Şi aşa a fost."
      },
      {
        "n": 10,
        "text": "Dumnezeu a numit uscatul pământ, iar grămada de ape a numit-o mări. Dumnezeu a văzut că lucrul acesta era bun."
      },
      {
        "n": 11,
        "text": "Apoi Dumnezeu a zis: „Să dea pământul verdeaţă, iarbă cu sămânţă, pomi roditori, care să facă rod după soiul lor şi care să aibă în ei sămânţa lor pe pământ.” Şi aşa a fost."
      },
      {
        "n": 12,
        "text": "Pământul a dat verdeaţă, iarbă cu sămânţă după soiul ei şi pomi care fac rod şi care îşi au sămânţa în ei, după soiul lor. Dumnezeu a văzut că lucrul acesta era bun."
      },
      {
        "n": 13,
        "text": "Astfel, a fost o seară, şi apoi a fost o dimineaţă: aceasta a fost ziua a treia."
      },
      {
        "n": 14,
        "text": "Dumnezeu a zis: „Să fie nişte luminători în întinderea cerului, ca să despartă ziua de noapte; ei să fie nişte semne care să arate vremurile, zilele şi anii;"
      },
      {
        "n": 15,
        "text": "şi să slujească de luminători în întinderea cerului, ca să lumineze pământul.” Şi aşa a fost."
      },
      {
        "n": 16,
        "text": "Dumnezeu a făcut cei doi mari luminători, şi anume: luminătorul cel mai mare ca să stăpânească ziua, şi luminătorul cel mai mic ca să stăpânească noaptea; a făcut şi stelele."
      },
      {
        "n": 17,
        "text": "Dumnezeu i-a aşezat în întinderea cerului ca să lumineze pământul,"
      },
      {
        "n": 18,
        "text": "să stăpânească ziua şi noaptea şi să despartă lumina de întuneric. Dumnezeu a văzut că lucrul acesta era bun."
      }
    ]
  }
}
